FinderZ/.DS_Store
FinderZ/FinderZV2.py
FinderZ/__init__.py
finderz-2.1.2.dist-info/METADATA
finderz-2.1.2.dist-info/WHEEL
finderz-2.1.2.dist-info/licenses/LICENSE
finderz-2.1.2.dist-info/RECORD
