Metadata-Version: 2.1
Name: FinderZ
Version: 2.1.2
Summary: A library that extends file management functionality in Python with many useful features in order to save your time and make life easier!
Project-URL: Homepage, https://github.com/PatzEdi
Project-URL: Repository, https://github.com/PatzEdi/FinderZ
Project-URL: Bug Tracker, https://github.com/PatzEdi/FinderZ/issues
Author-email: PatzEdi <patzedigithub@gmail.com>
License-Expression: GPL-3.0-or-later
License-File: LICENSE
Keywords: development,filemanagement,files,library
Classifier: License :: OSI Approved :: GNU General Public License v3 or later (GPLv3+)
Classifier: Operating System :: OS Independent
Classifier: Programming Language :: Python :: 3
Requires-Python: >=3.9
